[
    {
        "nome": "melissa ",
        "email": "melissa@email.com",
        "senha": "$2b$11$Nm8U8XUKRtTUYaukCzxU8Oetddc2V.gGokHvkCPw47Cn8GDyb6vXK",
        "cpf": "142536728",
        "nascimento": "1995-03-23",
        "telefone": "21828379033",
        "genero": "feminino"
    },
    {
        "nome": "melissa ",
        "email": "melissa@email.com",
        "senha": "$2b$11$9bWDMYGkFwIreuAZEil89e3VriQnDTIyTmqBySXd9lhyqrl7Q7dgi",
        "cpf": "23234354",
        "nascimento": "",
        "telefone": "",
        "genero": "feminino"
    },
    {
        "nome": "Douglas Victor Menezes",
        "email": "dv@douglasvictor.com",
        "senha": "$2b$11$tkvyU1nJ7fbh/TxJX9yAH.JcZl1KSbFte/W.8uc9lUiCcS1gZhZ82",
        "cpf": "00000000022",
        "nascimento": "1985-01-13",
        "telefone": "(51) 99669-6668",
        "genero": "masculino"
    }
]